ventu/__init__.py
ventu/config.py
ventu/protocol.py
ventu/service.py
ventu/ventu.py
ventu-0.4.5.dist-info/METADATA
ventu-0.4.5.dist-info/WHEEL
ventu-0.4.5.dist-info/entry_points.txt
ventu-0.4.5.dist-info/top_level.txt
ventu-0.4.5.dist-info/RECORD
