Metadata-Version: 2.1
Name: ventu
Version: 0.4.5
Summary: Host your deep learning models easily.
Home-page: https://github.com/kemingy/ventu
Author: Keming Yang
Author-email: kemingy94@gmail.com
License: UNKNOWN
Platform: UNKNOWN
Classifier: Programming Language :: Python :: 3 :: Only
Classifier: Programming Language :: Python :: 3.6
Classifier: Programming Language :: Python :: 3.7
Classifier: Programming Language :: Python :: 3.8
Classifier: Operating System :: OS Independent
Classifier: Topic :: Software Development :: Libraries :: Python Modules
Requires-Python: >=3.6
Requires-Dist: falcon (==2.0.0)
Requires-Dist: spectree (>=0.3.3)
Requires-Dist: pydantic (>=1.5.1)
Requires-Dist: msgpack (>=1.0.0)
Requires-Dist: prometheus-client (>=0.7.1)
